clld_markdown_plugin/__init__.py
clld_markdown_plugin-0.5.0.dist-info/LICENSE
clld_markdown_plugin-0.5.0.dist-info/METADATA
clld_markdown_plugin-0.5.0.dist-info/WHEEL
clld_markdown_plugin-0.5.0.dist-info/top_level.txt
clld_markdown_plugin-0.5.0.dist-info/RECORD
