Metadata-Version: 2.1
Name: clld-markdown-plugin
Version: 0.5.0
Summary: Render CLDF markdown in clld apps.
Home-page: https://github.com/clld/clld-markdown-plugin
Author: Robert Forkel, Florian Matter
Author-email: robert_forkel@eva.mpg.de, florianmatter@gmail.com
Project-URL: Bug Tracker, https://github.com/clld/clld-markdown-plugin/issues
Classifier: Development Status :: 2 - Pre-Alpha
Classifier: Intended Audience :: Science/Research
Classifier: License :: OSI Approved :: Apache Software License
Classifier: Natural Language :: English
Classifier: Programming Language :: Python :: 3
Classifier: Programming Language :: Python :: 3.8
Classifier: Programming Language :: Python :: 3.9
Classifier: Programming Language :: Python :: 3.10
Classifier: Programming Language :: Python :: 3.11
Classifier: Programming Language :: Python :: 3.12
License-File: LICENSE
Requires-Dist: clldutils
Requires-Dist: pycldf
Requires-Dist: clld
Requires-Dist: markdown
Provides-Extra: dev
Requires-Dist: flake8 ; extra == 'dev'
Requires-Dist: twine ; extra == 'dev'
Requires-Dist: wheel ; extra == 'dev'
Requires-Dist: build ; extra == 'dev'
Provides-Extra: test
Requires-Dist: pytest ; extra == 'test'
Requires-Dist: pytest-mock ; extra == 'test'
Requires-Dist: pytest-cov ; extra == 'test'
Requires-Dist: tox ; extra == 'test'
